AUTHORS
LICENSE
MANIFEST.in
README.rst
setup.cfg
setup.py
mockito/__init__.py
mockito/inorder.py
mockito/invocation.py
mockito/matchers.py
mockito/mock_registry.py
mockito/mocking.py
mockito/mockito.py
mockito/spying.py
mockito/verification.py
mockito_test/__init__.py
mockito_test/classmethods_test.py
mockito_test/demo_test.py
mockito_test/instancemethods_test.py
mockito_test/matchers_test.py
mockito_test/mockingexacttypes_test.py
mockito_test/modulefunctions_test.py
mockito_test/spying_test.py
mockito_test/staticmethods_test.py
mockito_test/stubbing_test.py
mockito_test/test_base.py
mockito_test/verification_errors_test.py
mockito_test/verifications_test.py
mockito_util/__init__.py
mockito_util/test.py
mockito_util/write_readme.py
mockito_without_hardcoded_distribute_version.egg-info/PKG-INFO
mockito_without_hardcoded_distribute_version.egg-info/SOURCES.txt
mockito_without_hardcoded_distribute_version.egg-info/dependency_links.txt
mockito_without_hardcoded_distribute_version.egg-info/top_level.txt