Metadata-Version: 1.1
Name: mockito-without-hardcoded-distribute-version
Version: 0.5.3
Summary: Spying framework
Home-page: https://github.com/mriehl/mockito-without-hardcoded-distribute-version
Author: Justin Hopper
Author-email: mockito-python@googlegroups.com
License: MIT
Platform: UNKNOWN
Classifier: Development Status :: 4 - Beta
Classifier: Intended Audience :: Developers
Classifier: License :: OSI Approved :: MIT License
Classifier: Topic :: Software Development :: Testing
Classifier: Programming Language :: Python :: 3
